_viteo.cpython-313-darwin.so
viteo/__init__.py
viteo-0.1.0rc0.dist-info/METADATA
viteo-0.1.0rc0.dist-info/WHEEL
viteo-0.1.0rc0.dist-info/licenses/LICENSE
viteo-0.1.0rc0.dist-info/RECORD
