Metadata-Version: 2.1
Name: viteo
Version: 0.1.0rc0
Summary: Hardware-accelerated video frame extraction for Apple Silicon
Keywords: video,frame,apple,mac,hardware-acceleration,mlx,avfoundation,videotoolbox
Author-Email: =?utf-8?b?UsOpbWkgSMOpbmVhdWx0?= <remi@heneault.fr>
License: MIT
Classifier: Development Status :: 4 - Beta
Classifier: Intended Audience :: Developers
Classifier: License :: OSI Approved :: MIT License
Classifier: Operating System :: MacOS :: MacOS X
Classifier: Programming Language :: C++
Classifier: Programming Language :: Objective C
Classifier: Programming Language :: Python :: 3
Classifier: Programming Language :: Python :: 3.10
Classifier: Programming Language :: Python :: 3.11
Classifier: Programming Language :: Python :: 3.12
Classifier: Programming Language :: Python :: 3.13
Classifier: Topic :: Multimedia :: Video
Classifier: Topic :: Software Development :: Libraries
Classifier: Topic :: Utilities
Project-URL: Homepage, https://github.com/codeSamuraii/viteo
Project-URL: Repository, https://github.com/codeSamuraii/viteo
Project-URL: Documentation, https://github.com/codeSamuraii/viteo#readme
Project-URL: Issues, https://github.com/codeSamuraii/viteo/issues
Requires-Python: >=3.10
Requires-Dist: mlx>=0.5.0
Provides-Extra: dev
Requires-Dist: pytest>=8.0; extra == "dev"
Requires-Dist: rich>=13.0; extra == "dev"
Requires-Dist: numpy>=1.24.0; extra == "dev"
